nomade/__init__.py
nomade/cli.py
nomade/community.py
nomade/demo.py
nomade/install.py
nomade/alerts/__init__.py
nomade/alerts/backends.py
nomade/alerts/dispatcher.py
nomade/alerts/thresholds.py
nomade/analysis/__init__.py
nomade/analysis/derivatives.py
nomade/analysis/similarity.py
nomade/collectors/__init__.py
nomade/collectors/base.py
nomade/collectors/disk.py
nomade/collectors/gpu.py
nomade/collectors/interactive.py
nomade/collectors/iostat.py
nomade/collectors/job_metrics.py
nomade/collectors/mpstat.py
nomade/collectors/nfs.py
nomade/collectors/node_state.py
nomade/collectors/slurm.py
nomade/collectors/slurm_legacy.py
nomade/collectors/vmstat.py
nomade/config/__init__.py
nomade/config/default.toml
nomade/db/__init__.py
nomade/db/schema.sql
nomade/hooks/__init__.py
nomade/hooks/prolog.py
nomade/ml/__init__.py
nomade/ml/autoencoder.py
nomade/ml/continuous.py
nomade/ml/ensemble.py
nomade/ml/gnn.py
nomade/ml/gnn_torch.py
nomade/ml/lstm.py
nomade/ml/persistence.py
nomade/monitors/__init__.py
nomade/monitors/job_monitor.py
nomade/prediction/__init__.py
nomade/viz/__init__.py
nomade/viz/dashboard.py
nomade/viz/server.py
nomade_hpc-1.1.0.dist-info/licenses/LICENSE
nomade_hpc-1.1.0.dist-info/METADATA
nomade_hpc-1.1.0.dist-info/WHEEL
nomade_hpc-1.1.0.dist-info/entry_points.txt
nomade_hpc-1.1.0.dist-info/top_level.txt
nomade_hpc-1.1.0.dist-info/RECORD
