Metadata-Version: 2.4
Name: nomade-hpc
Version: 1.1.0
Summary: A lightweight HPC monitoring and predictive analytics tool
Author-email: Joao Tonini <jtonini@richmond.edu>
Maintainer-email: Joao Tonini <jtonini@richmond.edu>
License: AGPL-3.0-or-later
Project-URL: Homepage, https://github.com/jtonini/nomade
Project-URL: Documentation, https://github.com/jtonini/nomade#readme
Project-URL: Repository, https://github.com/jtonini/nomade
Project-URL: Issues, https://github.com/jtonini/nomade/issues
Keywords: hpc,monitoring,slurm,cluster,predictive-analytics,machine-learning,anomaly-detection,graph-neural-network
Classifier: Development Status :: 4 - Beta
Classifier: Environment :: Console
Classifier: Intended Audience :: System Administrators
Classifier: Intended Audience :: Science/Research
Classifier: Operating System :: POSIX :: Linux
Classifier: Programming Language :: Python :: 3
Classifier: Programming Language :: Python :: 3.9
Classifier: Programming Language :: Python :: 3.10
Classifier: Programming Language :: Python :: 3.11
Classifier: Programming Language :: Python :: 3.12
Classifier: Topic :: System :: Monitoring
Classifier: Topic :: System :: Systems Administration
Classifier: Topic :: Scientific/Engineering
Requires-Python: >=3.9
License-File: LICENSE
Requires-Dist: click>=8.0
Requires-Dist: toml>=0.10
Requires-Dist: numpy>=1.21
Requires-Dist: pandas>=1.3
Requires-Dist: scipy>=1.7
Provides-Extra: ml
Requires-Dist: scikit-learn>=1.0; extra == "ml"
Requires-Dist: torch>=2.0; extra == "ml"
Requires-Dist: torch-geometric>=2.0; extra == "ml"
Provides-Extra: dashboard
Requires-Dist: jinja2>=3.0; extra == "dashboard"
Provides-Extra: alerts
Provides-Extra: all
Requires-Dist: nomade[dashboard,ml]; extra == "all"
Provides-Extra: dev
Requires-Dist: pytest>=7.0; extra == "dev"
Requires-Dist: pytest-cov>=4.0; extra == "dev"
Requires-Dist: ruff>=0.1; extra == "dev"
Requires-Dist: black>=23.0; extra == "dev"
Requires-Dist: mypy>=1.0; extra == "dev"
Requires-Dist: pre-commit>=3.0; extra == "dev"
Dynamic: license-file
